scrimmage_sdk/__init__.py
scrimmage_sdk/container.py
scrimmage_sdk/create.py
scrimmage_sdk/scrimmage.py
scrimmage_sdk/components/__init__.py
scrimmage_sdk/components/api.py
scrimmage_sdk/components/config.py
scrimmage_sdk/components/logger.py
scrimmage_sdk/components/reward.py
scrimmage_sdk/components/status.py
scrimmage_sdk/components/user.py
scrimmage_sdk/exceptions/__init__.py
scrimmage_sdk/schema/__init__.py
scrimmage_sdk/schema/logger.py
scrimmage_sdk/schema/private_key.py
scrimmage_sdk/schema/rewarder_config.py
scrimmage_sdk/schema/services.py
tests/__init__.py
tests/test_main.py
scrimmage_sdk-1.1.0.dist-info/LICENSE.txt
scrimmage_sdk-1.1.0.dist-info/METADATA
scrimmage_sdk-1.1.0.dist-info/WHEEL
scrimmage_sdk-1.1.0.dist-info/top_level.txt
scrimmage_sdk-1.1.0.dist-info/RECORD
