Metadata-Version: 2.1
Name: scrimmage-sdk
Version: 1.1.0
Summary: Simple rewards for your app or website
Home-page: https://github.com/Scrimmage-co/python-sdk
Author: Scrimmage Co <founders@scrimmage.co>
Author-email: founders@scrimmage.co
License: MIT
Keywords: scrimmage,reward,rewards,loyalty,api,sdk,python
Classifier: Programming Language :: Python :: 3
Classifier: License :: OSI Approved :: MIT License
Classifier: Operating System :: OS Independent
Requires-Python: >=3.6
License-File: LICENSE.txt
Requires-Dist: dependency-injector
Requires-Dist: httpx
Requires-Dist: pydantic
